pydllfile/__init__.py
pydllfile/dllist.py
pydllfile/hexdump.py
pydllfile-0.0.4.dist-info/LICENSE.md
pydllfile-0.0.4.dist-info/METADATA
pydllfile-0.0.4.dist-info/WHEEL
pydllfile-0.0.4.dist-info/top_level.txt
pydllfile-0.0.4.dist-info/RECORD
