Metadata-Version: 2.1
Name: pydllfile
Version: 0.0.4
Summary: pydllfile - python double linked list file storage memory management
Home-page: https://github.com/kr-g/pydllfile
Author: k.r. goger
Author-email: k.r.goger+pydllfile@gmail.com
License: UNKNOWN
Keywords: double linked list file storage memory management pyheapfile
Platform: UNKNOWN
Classifier: Development Status :: 3 - Alpha
Classifier: Operating System :: POSIX :: Linux
Classifier: Intended Audience :: Developers
Classifier: Programming Language :: Python :: 3
Classifier: License :: OSI Approved :: GNU Affero General Public License v3 or later (AGPLv3+)
Requires-Python: >=3.6
Requires-Dist: pyheapfile
